tracardi/__init__.py
tracardi/config.py
tracardi/requirements.txt
tracardi/data/initail_data.py
tracardi/domain/__init__.py
tracardi/domain/agg_result.py
tracardi/domain/api_instance.py
tracardi/domain/consent_type.py
tracardi/domain/console.py
tracardi/domain/context.py
tracardi/domain/credentials.py
tracardi/domain/entity.py
tracardi/domain/event.py
tracardi/domain/event_metadata.py
tracardi/domain/event_payload_validator.py
tracardi/domain/event_source.py
tracardi/domain/event_tag.py
tracardi/domain/events.py
tracardi/domain/flow.py
tracardi/domain/flow_action_plugin.py
tracardi/domain/flow_meta_data.py
tracardi/domain/metadata.py
tracardi/domain/named_entity.py
tracardi/domain/pii.py
tracardi/domain/plugin_import.py
tracardi/domain/pro_service_config.py
tracardi/domain/profile.py
tracardi/domain/profile_stats.py
tracardi/domain/profile_traits.py
tracardi/domain/project.py
tracardi/domain/query_result.py
tracardi/domain/resource.py
tracardi/domain/response.py
tracardi/domain/rule.py
tracardi/domain/schedule.py
tracardi/domain/segment.py
tracardi/domain/segments.py
tracardi/domain/session.py
tracardi/domain/settings.py
tracardi/domain/sql_query.py
tracardi/domain/stat_payload.py
tracardi/domain/storage_aggregate_result.py
tracardi/domain/storage_result.py
tracardi/domain/task.py
tracardi/domain/third_party_processor.py
tracardi/domain/time.py
tracardi/domain/time_range_query.py
tracardi/domain/token.py
tracardi/domain/tracardi_pro_endpoint.py
tracardi/domain/tracker.py
tracardi/domain/type.py
tracardi/domain/user.py
tracardi/domain/user_consent.py
tracardi/domain/__pycache__/__init__.cpython-38.pyc
tracardi/domain/__pycache__/agg_result.cpython-38.pyc
tracardi/domain/__pycache__/api_instance.cpython-38.pyc
tracardi/domain/__pycache__/consent_schema.cpython-38.pyc
tracardi/domain/__pycache__/consent_type.cpython-38.pyc
tracardi/domain/__pycache__/console.cpython-38.pyc
tracardi/domain/__pycache__/context.cpython-38.pyc
tracardi-0.6.26.dist-info/LICENSE.md
tracardi-0.6.26.dist-info/METADATA
tracardi-0.6.26.dist-info/WHEEL
tracardi-0.6.26.dist-info/top_level.txt
tracardi-0.6.26.dist-info/RECORD
