Metadata-Version: 2.1
Name: tracardi
Version: 0.6.26
Summary: Tracardi Customer Data Platform backend
Home-page: UNKNOWN
Author: Risto Kowaczewski
Author-email: risto.kowaczewski@gmail.com
License: UNKNOWN
Keywords: tracardi
Platform: UNKNOWN
Classifier: Programming Language :: Python :: 3
Classifier: License :: OSI Approved :: MIT License
Classifier: Operating System :: OS Independent
Requires-Python: >=3.8
License-File: LICENSE.md
Requires-Dist: pip (>=21.2.4)
Requires-Dist: pydantic
Requires-Dist: aiohttp
Requires-Dist: aiohttp[speedups]
Requires-Dist: redis
Requires-Dist: aioredis
Requires-Dist: elasticsearch[async] (==7.10.1)
Requires-Dist: prodict (>=0.8.18)
Requires-Dist: tzlocal
Requires-Dist: python-multipart (>=0.0.5)
Requires-Dist: lark (>=0.11.3)
Requires-Dist: dateparser
Requires-Dist: dotty-dict (==1.3.0)
Requires-Dist: pytz
Requires-Dist: device-detector (==5.0.1)
Requires-Dist: deepdiff (>=5.5.0)
Requires-Dist: tracardi-plugin-sdk (>=0.6.30)
Requires-Dist: tracardi-graph-runner (>=0.6.9)
Requires-Dist: tracardi-dot-notation (>=0.6.6)
Requires-Dist: pytimeparse
Requires-Dist: barcodenumber
Requires-Dist: astral
Requires-Dist: jsonschema
Requires-Dist: python-dateutil
Requires-Dist: mailchimp-transactional
Requires-Dist: email-validator
Requires-Dist: lxml
Requires-Dist: beautifulsoup4
Requires-Dist: names (==0.3.0)
Requires-Dist: motor (~=2.5.0)
